{
"#import": {
    "constants.caf.json": ""
},

"scene": {
    "AbsoluteStyle": {
        "dims": {"width": {"Vw": 100.0}, "height": {"Vh": 100.0}},
        "content": {"flex_direction": "Column", "justify_main": "Center", "justify_cross": "Center"}
    },
    "BgColor": [{"Hsla": {"hue": 214.0, "saturation": 0.12, "lightness": 0.22, "alpha": 1.0}}],

    "header": {
        "AbsoluteStyle": {
            "dims": {"width": {"Percent": 100.0}, "height": {"Percent": 90.0}},
            "content": {"flex_direction": "Column", "justify_main": "Center", "justify_cross": "Center"}
        },

        "day": {
            "text": {
                "TextLine": {"size": 50.0, "linebreak": "WordBoundary", "justify": "Center"}
            }
        },

        "karma": {
            "FlexStyle": {
                "flex": {
                    "margin": {
                        "top": {"Px": 20.0}
                    }
                }
            },

            "text": {
                "TextLine": {"size": 35.0}
            }
        }
    },

    "content": {
        "FlexStyle": {
            "flex": {"flex_grow": 1.0}
        }
    },

    "footer": {
        "FlexStyle": {
            "dims": {"min_height": {"Percent": 20.0}, "width": {"Percent": 100.0}},
            "content": {"flex_direction": "Row", "justify_main": "Center", "justify_cross": "FlexEnd"}
        },

        "fill": {
            "FlexStyle": {
                "flex": {"flex_grow": 1.0}
            }
        },

        "start_button": {
            "FlexStyle": {
                "dims": {"min_width": {"Px": 200.0}},
                "content": {"justify_main": "Center", "justify_cross": "Center"},
                "flex": {"margin": {"bottom": {"Px": 40.0}, "right": {"Px": 40.0}}}
            },
            "Splat<Border>": [{"Px": 3.0}],
            "BrRadius": [{"Px": 13.0}],
            "BrColor": [{"Hsla": {"hue": 32.0, "saturation": 0.7, "lightness": 0.2, "alpha": 1.0}}],
            "Interactive": [],
            "Animated<BgColor>": {
                "values": {
                    "idle": {"Hsla": {"hue": 32.0, "saturation": 0.5, "lightness": 0.45, "alpha": 1.0}},
                    "hover": {"Hsla": {"hue": 32.0, "saturation": 0.6, "lightness": 0.4, "alpha": 1.0}}
                },
                "settings": {
                    "pointer_enter": {"duration": 0.15, "easing": "OutExpo"},
                    "pointer_leave": {"duration": 0.15, "easing": "OutExpo"}
                }
            },

            "text": {
                "FlexStyle": {
                    "flex": {"margin": {"top": {"Px": 17.0}, "bottom": {"Px": 17.0}, "left": {"Px": 10.0}, "right": {"Px": 10.0}}}
                },
                "TextLine": {"text": "Start Day"}
            }
        }
    }
}
}
